<?xml version="1.0" encoding="UTF-8"?>
<strategy_2_Hatch_Lurker__vs__Terran_>
    <build_order>
        <unit>
            <supply>9</supply>
            <type>overlord</type>
        </unit>
        <building>
            <supply>12</supply>
            <type>hatchery</type>
        </building>
        <building>
            <supply>11</supply>
            <type>spawning pool</type>
        </building>
        <building>
            <supply>10</supply>
            <type>extractor</type>
        </building>
        <unit>
            <supply>16</supply>
            <type>overlord</type>
        </unit>
        <building>
            <type>lair</type>
        </building>
        <building>
            <type>hatchery</type>
        </building>
        <unit>
            <type>zergling</type>
        </unit>
        <unit>
            <supply>22</supply>
            <type>overlord</type>
        </unit>
        <unit>
            <percentage>
                <pct>50</pct>
                <type>lair</type>
            </percentage>
            <type>hydralisk</type>
        </unit>
        <building>
            <percentage>
                <pct>90</pct>
                <type>lair</type>
            </percentage>
            <type>extractor</type>
        </building>
        <unit>
            <percentage>
                <pct>100</pct>
                <type>lair</type>
            </percentage>
            <type>lurker</type>
        </unit>
        <building>
            <percentage>
                <pct>100</pct>
                <type>lair</type>
            </percentage>
            <type>spire</type>
        </building>
        <building>
            <percentage>
                <pct>100</pct>
                <type>lair</type>
            </percentage>
            <type>spire</type>
        </building>
        <unit>
            <type>lurker</type>
        </unit>
        <unit>
            <type>lurker</type>
        </unit>
        <building>
            <type>hatchery</type>
        </building>
        <building>
            <type>hatchery</type>
        </building>
        <countered_by>
            <soft>Sparks Terran</soft>
            <soft>Early Academy Builds</soft>
            <hard>2 Port Wraith Zerg</hard>
            <hard>1 Rax Gas</hard>
        </countered_by>
        <counter_to/>
        <maps>
            <strong>Medusa</strong>
        </maps>
    </build_order>
    <build_order>
        <unit>
            <supply>9</supply>
            <type>overlord</type>
        </unit>
        <building>
            <supply>12</supply>
            <type>spawning pool</type>
        </building>
        <building>
            <supply>11</supply>
            <type>extractor</type>
        </building>
        <building>
            <supply>11</supply>
            <type>hatchery</type>
        </building>
        <building>
            <type>lair</type>
        </building>
        <unit>
            <type>zergling</type>
        </unit>
        <building>
            <percentage>
                <pct>50</pct>
                <type>lair</type>
            </percentage>
            <percentage>
                <pct>50</pct>
                <type>hydralisk</type>
            </percentage>
            <percentage>
                <pct>50</pct>
                <type>hydralisk den</type>
            </percentage>
            <type>lair</type>
        </building>
        <unit>
            <percentage>
                <pct>50</pct>
                <type>lair</type>
            </percentage>
            <percentage>
                <pct>50</pct>
                <type>hydralisk</type>
            </percentage>
            <percentage>
                <pct>50</pct>
                <type>hydralisk den</type>
            </percentage>
            <type>hydralisk</type>
        </unit>
        <unit>
            <percentage>
                <pct>100</pct>
                <type>lurker</type>
            </percentage>
            <type>lurker</type>
        </unit>
        <countered_by>
            <soft>Sparks Terran</soft>
            <soft>Early Academy Builds</soft>
            <hard>2 Port Wraith Zerg</hard>
            <hard>1 Rax Gas</hard>
        </countered_by>
        <counter_to/>
        <maps>
            <strong>Medusa</strong>
        </maps>
    </build_order>
    <build_order>
        <building>
            <supply>9</supply>
            <type>spawning pool</type>
        </building>
        <unit>
            <supply>8</supply>
            <type>drone</type>
        </unit>
        <building>
            <supply>9</supply>
            <type>extractor</type>
        </building>
        <unit>
            <supply>8</supply>
            <type>drone</type>
        </unit>
        <building>
            <supply>9</supply>
            <type>extractor</type>
        </building>
        <unit>
            <supply>9</supply>
            <type>drone</type>
        </unit>
        <unit>
            <supply>10</supply>
            <type>overlord</type>
        </unit>
        <unit>
            <supply>10</supply>
            <type>scout</type>
        </unit>
        <unit>
            <supply>10</supply>
            <type>drone</type>
        </unit>
        <building>
            <supply>13</supply>
            <type>extractor</type>
        </building>
        <unit>
            <supply>12</supply>
            <type>drone</type>
        </unit>
        <building>
            <supply>13</supply>
            <type>hatchery</type>
        </building>
        <building>
            <supply>15</supply>
            <type>lair</type>
        </building>
        <building>
            <type>lair</type>
        </building>
        <unit>
            <type>hydralisk</type>
        </unit>
        <unit>
            <type>lurker</type>
        </unit>
        <unit>
            <type>hydralisk</type>
        </unit>
        <countered_by>
            <soft>Sparks Terran</soft>
            <soft>Early Academy Builds</soft>
            <hard>2 Port Wraith Zerg</hard>
            <hard>1 Rax Gas</hard>
        </countered_by>
        <counter_to>
            <soft>1 Rax FE</soft>
        </counter_to>
        <maps>
            <strong>Medusa</strong>
        </maps>
    </build_order>
</strategy_2_Hatch_Lurker__vs__Terran_>
